servicekit/.DS_Store
servicekit/__init__.py
servicekit/api/.DS_Store
servicekit/api/__init__.py
servicekit/api/app.py
servicekit/api/apps/.DS_Store
servicekit/api/apps/landing/index.html
servicekit/api/apps/landing/manifest.json
servicekit/api/auth.py
servicekit/api/crud.py
servicekit/api/dependencies.py
servicekit/api/middleware.py
servicekit/api/monitoring.py
servicekit/api/pagination.py
servicekit/api/registration.py
servicekit/api/router.py
servicekit/api/routers/__init__.py
servicekit/api/routers/health.py
servicekit/api/routers/job.py
servicekit/api/routers/metrics.py
servicekit/api/routers/system.py
servicekit/api/service_builder.py
servicekit/api/sse.py
servicekit/api/utilities.py
servicekit/database.py
servicekit/exceptions.py
servicekit/gunicorn.conf.py
servicekit/logging.py
servicekit/manager.py
servicekit/models.py
servicekit/py.typed
servicekit/repository.py
servicekit/scheduler.py
servicekit/schemas.py
servicekit/types.py
servicekit-0.8.1.dist-info/WHEEL
servicekit-0.8.1.dist-info/METADATA
servicekit-0.8.1.dist-info/RECORD
