Metadata-Version: 2.3
Name: servicekit
Version: 0.8.1
Summary: Async SQLAlchemy framework with FastAPI integration - reusable foundation for building data services
Keywords: fastapi,sqlalchemy,async,database,rest-api,crud,framework
Author: Morten Hansen
Author-email: Morten Hansen <morten@winterop.com>
License: AGPL-3.0-or-later
Classifier: Development Status :: 3 - Alpha
Classifier: Intended Audience :: Developers
Classifier: License :: OSI Approved :: GNU Affero General Public License v3 or later (AGPLv3+)
Classifier: Programming Language :: Python :: 3
Classifier: Programming Language :: Python :: 3.13
Classifier: Framework :: FastAPI
Classifier: Topic :: Software Development :: Libraries :: Python Modules
Classifier: Topic :: Database
Requires-Dist: aiosqlite>=0.21.0
Requires-Dist: alembic>=1.17.0
Requires-Dist: fastapi[standard]>=0.119.1
Requires-Dist: gunicorn>=23.0.0
Requires-Dist: opentelemetry-api>=1.37.0
Requires-Dist: opentelemetry-exporter-prometheus>=0.58b0
Requires-Dist: opentelemetry-instrumentation-fastapi>=0.58b0
Requires-Dist: opentelemetry-instrumentation-sqlalchemy>=0.58b0
Requires-Dist: opentelemetry-sdk>=1.37.0
Requires-Dist: pydantic>=2.12.0
Requires-Dist: python-ulid>=3.1.0
Requires-Dist: sqlalchemy[asyncio]>=2.0.43
Requires-Dist: structlog>=24.4.0
Requires-Python: >=3.13, <3.14
Project-URL: Documentation, https://winterop-com.github.io/servicekit
Project-URL: Homepage, https://github.com/winterop-com/servicekit
Project-URL: Issues, https://github.com/winterop-com/servicekit/issues
Project-URL: Repository, https://github.com/winterop-com/servicekit
